kstocks/__init__.py
kstocks-1.0.dist-info/LICENSE
kstocks-1.0.dist-info/METADATA
kstocks-1.0.dist-info/WHEEL
kstocks-1.0.dist-info/top_level.txt
kstocks-1.0.dist-info/RECORD
