Metadata-Version: 2.1
Name: kstocks
Version: 1.0
Summary: Korean Stock Module
Home-page: https://github.com/Tim232/kstocks
Author: Tim232
Author-email: endbot4023@gmail.com
License: GPL-V3
Keywords: stocks,korean,KOSPI,KOSDAQ
Platform: UNKNOWN
Requires-Python: >=3.8
Requires-Dist: scrapy
Requires-Dist: asyncio
Requires-Dist: aiohttp
